efficientnet/__init__.py
efficientnet/test.py
efficientnet_api-1.0.2.dist-info/METADATA
efficientnet_api-1.0.2.dist-info/WHEEL
efficientnet_api-1.0.2.dist-info/top_level.txt
efficientnet_api-1.0.2.dist-info/RECORD
