Metadata-Version: 2.1
Name: efficientnet-api
Version: 1.0.2
Summary: efficientnet module
Home-page: UNKNOWN
Author: wrd
License: UNKNOWN
Platform: UNKNOWN
